odoo/addons/account_bank_statement_import_move_line/README.rst
odoo/addons/account_bank_statement_import_move_line/__init__.py
odoo/addons/account_bank_statement_import_move_line/__manifest__.py
odoo/addons/account_bank_statement_import_move_line/i18n/account_bank_statement_import_move_line.pot
odoo/addons/account_bank_statement_import_move_line/i18n/de.po
odoo/addons/account_bank_statement_import_move_line/i18n/es.po
odoo/addons/account_bank_statement_import_move_line/i18n/fr.po
odoo/addons/account_bank_statement_import_move_line/i18n/hr.po
odoo/addons/account_bank_statement_import_move_line/i18n/nl.po
odoo/addons/account_bank_statement_import_move_line/i18n/pt_BR.po
odoo/addons/account_bank_statement_import_move_line/i18n/pt_PT.po
odoo/addons/account_bank_statement_import_move_line/i18n/sl.po
odoo/addons/account_bank_statement_import_move_line/models/__init__.py
odoo/addons/account_bank_statement_import_move_line/models/account_move_line.py
odoo/addons/account_bank_statement_import_move_line/readme/CONFIGURE.rst
odoo/addons/account_bank_statement_import_move_line/readme/CONTRIBUTORS.rst
odoo/addons/account_bank_statement_import_move_line/readme/DESCRIPTION.rst
odoo/addons/account_bank_statement_import_move_line/readme/USAGE.rst
odoo/addons/account_bank_statement_import_move_line/static/description/icon.png
odoo/addons/account_bank_statement_import_move_line/static/description/index.html
odoo/addons/account_bank_statement_import_move_line/tests/__init__.py
odoo/addons/account_bank_statement_import_move_line/tests/test_account_bank_statement_import_move_line.py
odoo/addons/account_bank_statement_import_move_line/views/account_bank_statement_view.xml
odoo/addons/account_bank_statement_import_move_line/wizards/__init__.py
odoo/addons/account_bank_statement_import_move_line/wizards/account_statement_line_create.py
odoo/addons/account_bank_statement_import_move_line/wizards/account_statement_line_create_view.xml
odoo12_addon_account_bank_statement_import_move_line-12.0.1.0.0.99.dev7.dist-info/METADATA
odoo12_addon_account_bank_statement_import_move_line-12.0.1.0.0.99.dev7.dist-info/WHEEL
odoo12_addon_account_bank_statement_import_move_line-12.0.1.0.0.99.dev7.dist-info/top_level.txt
odoo12_addon_account_bank_statement_import_move_line-12.0.1.0.0.99.dev7.dist-info/RECORD
